perst/__init__.py
perst/conftest.py
perst/elems/__init__.py
perst/elems/elems.py
perst/elems/elems_test.py
perst/elems/elems_testutil.py
perst/elems/impl/__init__.py
perst/elems/impl/json_elems.py
perst/elems/impl/json_elems_test.py
perst/elems/impl/peewee_elems.py
perst/elems/impl/peewee_elems_test.py
perst-0.1.8.dist-info/METADATA
perst-0.1.8.dist-info/WHEEL
perst-0.1.8.dist-info/top_level.txt
perst-0.1.8.dist-info/RECORD
