Metadata-Version: 2.2
Name: perst
Version: 0.1.8
Summary: Simple persistance library
Requires-Python: >=3.8
Requires-Dist: pytest>=8.3.4
